<annotation>
	<folder>1</folder>
	<filename>16.png</filename>
	<path>/home/durra/human detection dataset/1/16.png</path>
	<source>
		<database>Unknown</database>
	</source>
	<size>
		<width>723</width>
		<height>589</height>
		<depth>3</depth>
	</size>
	<segmented>0</segmented>
	<object>
		<name>human</name>
		<pose>Unspecified</pose>
		<truncated>0</truncated>
		<difficult>0</difficult>
		<bndbox>
			<xmin>274</xmin>
			<ymin>284</ymin>
			<xmax>374</xmax>
			<ymax>527</ymax>
		</bndbox>
	</object>
</annotation>
